easyexplore/__init__.py
easyexplore/anomaly_detector.py
easyexplore/data_explorer.py
easyexplore/data_import_export.py
easyexplore/data_visualizer.py
easyexplore/interactive_visualizer.py
easyexplore/unsupervised_machine_learning.py
easyexplore/utils.py
easyexplore-0.7.4.dist-info/LICENSE
easyexplore-0.7.4.dist-info/METADATA
easyexplore-0.7.4.dist-info/WHEEL
easyexplore-0.7.4.dist-info/top_level.txt
easyexplore-0.7.4.dist-info/RECORD
