Metadata-Version: 2.1
Name: easyexplore
Version: 0.7.4
Summary: Toolbox for easy and effective data exploration
Home-page: https://github.com/GianniBalistreri/easyexplore
Author: Gianni Francesco Balistreri
Author-email: gbalistreri@gmx.de
License: GNU
Keywords: data-exploration interactive-visualization plotly machine-learning
Classifier: Programming Language :: Python :: 3
Classifier: Programming Language :: Python :: 3.6
Classifier: Programming Language :: Python :: 3.7
Classifier: Programming Language :: Python :: 3.8
Classifier: Operating System :: OS Independent
Requires-Python: >=3.6
License-File: LICENSE
Requires-Dist: boto3 (==1.17.0)
Requires-Dist: dask (==2021.10.0)
Requires-Dist: fsspec (==0.8.5)
Requires-Dist: geojson (==2.5.0)
Requires-Dist: google-cloud-storage (==1.36.1)
Requires-Dist: ipywidgets (==7.5.1)
Requires-Dist: joblib (==1.2.0)
Requires-Dist: kaleido (==0.2.1)
Requires-Dist: networkx (==2.5)
Requires-Dist: numpy (==1.22.0)
Requires-Dist: pandas (==1.2.0)
Requires-Dist: plotly (==4.11.0)
Requires-Dist: pyarrow (==2.0.0)
Requires-Dist: pyLDAvis (==3.3.1)
Requires-Dist: pyod (==0.8.2)
Requires-Dist: s3fs (==0.4.0)
Requires-Dist: scikit-image (==0.19.2)
Requires-Dist: scipy (==1.5.2)
Requires-Dist: scikit-learn (==0.23.2)
Requires-Dist: sqlalchemy (==1.3.19)
Requires-Dist: statsmodels (==0.12.0)
Requires-Dist: toolz (==0.11.1)
Requires-Dist: wheel (==0.38.1)
Requires-Dist: xlrd (==1.2.0)
